wata/__init__.py
wata/client.py
wata/core.py
wata/exceptions.py
wata/http.py
wata/modules/__init__.py
wata/modules/base.py
wata/modules/payments.py
wata/modules/steam.py
wata/modules/webhooks.py
wata_api-0.1.9.dist-info/METADATA
wata_api-0.1.9.dist-info/WHEEL
wata_api-0.1.9.dist-info/top_level.txt
wata_api-0.1.9.dist-info/RECORD
